sendtowev/__init__.py
sendtowev/main.py
sendtowev-0.4.dist-info/METADATA
sendtowev-0.4.dist-info/WHEEL
sendtowev-0.4.dist-info/top_level.txt
sendtowev-0.4.dist-info/RECORD
