Metadata-Version: 2.1
Name: sendtowev
Version: 0.4
Summary: Some package
Author: 
Author-email: 
Classifier: Programming Language :: Python :: 3
Classifier: License :: OSI Approved :: MIT License
Classifier: Operating System :: OS Independent
Requires-Dist: requests
